drpg/__init__.py
drpg/__main__.py
drpg/api.py
drpg/cmd.py
drpg/config.py
drpg/py.typed
drpg/sync.py
drpg/types.py
drpg-2025.7.8.dist-info/METADATA
drpg-2025.7.8.dist-info/WHEEL
drpg-2025.7.8.dist-info/entry_points.txt
drpg-2025.7.8.dist-info/licenses/LICENSE
drpg-2025.7.8.dist-info/RECORD
