Metadata-Version: 2.4
Name: drpg
Version: 2025.7.8
Summary: Download and keep up to date your purchases from DriveThruRPG
Project-URL: Changelog, https://github.com/glujan/drpg/blob/master/CHANGELOG.md
Project-URL: GitHub, https://github.com/glujan/drpg
Project-URL: Homepage, https://github.com/glujan/drpg
Author: Grzegorz Janik
License-Expression: MIT
License-File: LICENSE
Classifier: Development Status :: 5 - Production/Stable
Classifier: License :: OSI Approved :: MIT License
Classifier: Operating System :: OS Independent
Classifier: Programming Language :: Python :: 3
Classifier: Programming Language :: Python :: 3 :: Only
Classifier: Programming Language :: Python :: Implementation :: CPython
Requires-Python: >=3.9
Requires-Dist: httpx-retries>=0.4.0
Requires-Dist: httpx[http2]>=0.27
